setup.cfg
setup.py
PyMoneris.egg-info/PKG-INFO
PyMoneris.egg-info/SOURCES.txt
PyMoneris.egg-info/dependency_links.txt
PyMoneris.egg-info/entry_points.txt
PyMoneris.egg-info/not-zip-safe
PyMoneris.egg-info/top_level.txt
docs/license.txt
pymoneris/__init__.py
pymoneris/eselectplus/__init__.py
pymoneris/eselectplus/api.py
pymoneris/eselectplus/helpers.py
pymoneris/eselectplus/interface.py
tests/test_eselectplus.py