Metadata-Version: 1.1
Name: PyMoneris
Version: 0.1r3dev-r8
Summary: A Python interface to Moneris APIs.
Home-page: http://code.google.com/p/pymoneris/
Author: J Kenneth King
Author-email: james@agentultra.com
License: LGPL
Keywords: ecommerce,moneris,eselectplus
Platform: UNKNOWN
Classifier: Development Status :: 5 - Production/Stable
Classifier: Intended Audience :: Developers
Classifier: License :: OSI Approved :: GNU Library or Lesser General Public License (LGPL)
Classifier: Topic :: Other/Nonlisted Topic
